<?xml version="1.0" encoding="UTF-8"?>
<activity id="138" moduleid="187" modulename="lesson" contextid="198">
  <lesson id="138">
    <course>2</course>
    <name>Lesson 5.8 Teacher Guide: Exponential Situations as Functions</name>
    <intro></intro>
    <introformat>1</introformat>
    <practice>1</practice>
    <modattempts>0</modattempts>
    <usepassword>0</usepassword>
    <password></password>
    <dependency>0</dependency>
    <conditions>O:8:"stdClass":3:{s:9:"timespent";i:0;s:9:"completed";i:0;s:15:"gradebetterthan";i:0;}</conditions>
    <grade>0</grade>
    <custom>1</custom>
    <ongoing>0</ongoing>
    <usemaxgrade>0</usemaxgrade>
    <maxanswers>5</maxanswers>
    <maxattempts>0</maxattempts>
    <review>0</review>
    <nextpagedefault>0</nextpagedefault>
    <feedback>0</feedback>
    <minquestions>0</minquestions>
    <maxpages>1</maxpages>
    <timelimit>0</timelimit>
    <retake>1</retake>
    <activitylink>188</activitylink>
    <mediafile></mediafile>
    <mediaheight>480</mediaheight>
    <mediawidth>640</mediawidth>
    <mediaclose>0</mediaclose>
    <slideshow>0</slideshow>
    <width>640</width>
    <height>480</height>
    <bgcolor>#FFFFFF</bgcolor>
    <displayleft>1</displayleft>
    <displayleftif>0</displayleftif>
    <progressbar>0</progressbar>
    <available>0</available>
    <deadline>0</deadline>
    <timemodified>1690400578</timemodified>
    <completionendreached>0</completionendreached>
    <completiontimespent>0</completiontimespent>
    <allowofflineattempts>0</allowofflineattempts>
    <pages>
      <page id="1304">
        <prevpageid>0</prevpageid>
        <nextpageid>1305</nextpageid>
        <qtype>20</qtype>
        <qoption>0</qoption>
        <layout>1</layout>
        <display>1</display>
        <timecreated>1662401170</timecreated>
        <timemodified>1663710425</timemodified>
        <title>5.8.0: Lesson Overview</title>
        <contents>&lt;div class="os-raise-content" data-content-id="fc2ffc87-fcc9-4590-a460-dd55abd00a62"&gt;&lt;/div&gt;</contents>
        <contentsformat>1</contentsformat>
        <answers>
          <answer id="2933">
            <jumpto>-1</jumpto>
            <grade>0</grade>
            <score>0</score>
            <flags>0</flags>
            <timecreated>1662401170</timecreated>
            <timemodified>0</timemodified>
            <answer_text>Next</answer_text>
            <response>$@NULL@$</response>
            <answerformat>0</answerformat>
            <responseformat>0</responseformat>
            <attempts>
            </attempts>
          </answer>
        </answers>
        <branches>
        </branches>
      </page>
      <page id="1305">
        <prevpageid>1304</prevpageid>
        <nextpageid>1306</nextpageid>
        <qtype>20</qtype>
        <qoption>0</qoption>
        <layout>1</layout>
        <display>1</display>
        <timecreated>1662401541</timecreated>
        <timemodified>1663518290</timemodified>
        <title>5.8.1: Meaning of a Function Presented Graphically</title>
        <contents>&lt;div class="os-raise-content" data-content-id="ef3c9aa1-f939-4c87-81ac-e46b8db0a269"&gt;&lt;/div&gt;</contents>
        <contentsformat>1</contentsformat>
        <answers>
          <answer id="2934">
            <jumpto>-40</jumpto>
            <grade>0</grade>
            <score>0</score>
            <flags>0</flags>
            <timecreated>1662401541</timecreated>
            <timemodified>0</timemodified>
            <answer_text>Previous</answer_text>
            <response>$@NULL@$</response>
            <answerformat>0</answerformat>
            <responseformat>0</responseformat>
            <attempts>
            </attempts>
          </answer>
          <answer id="2935">
            <jumpto>-1</jumpto>
            <grade>0</grade>
            <score>0</score>
            <flags>0</flags>
            <timecreated>1662401541</timecreated>
            <timemodified>0</timemodified>
            <answer_text>Next</answer_text>
            <response>$@NULL@$</response>
            <answerformat>0</answerformat>
            <responseformat>0</responseformat>
            <attempts>
            </attempts>
          </answer>
        </answers>
        <branches>
        </branches>
      </page>
      <page id="1306">
        <prevpageid>1305</prevpageid>
        <nextpageid>1307</nextpageid>
        <qtype>20</qtype>
        <qoption>0</qoption>
        <layout>1</layout>
        <display>1</display>
        <timecreated>1662402081</timecreated>
        <timemodified>1663665977</timemodified>
        <title>5.8.2: Represent a Function as a Table of Values, Graph, and Equation</title>
        <contents>&lt;div class="os-raise-content" data-content-id="489fd58b-4956-48d2-b479-ee9aed511050"&gt;&lt;/div&gt;</contents>
        <contentsformat>1</contentsformat>
        <answers>
          <answer id="2936">
            <jumpto>-40</jumpto>
            <grade>0</grade>
            <score>0</score>
            <flags>0</flags>
            <timecreated>1662402081</timecreated>
            <timemodified>0</timemodified>
            <answer_text>Previous</answer_text>
            <response>$@NULL@$</response>
            <answerformat>0</answerformat>
            <responseformat>0</responseformat>
            <attempts>
            </attempts>
          </answer>
          <answer id="2937">
            <jumpto>-1</jumpto>
            <grade>0</grade>
            <score>0</score>
            <flags>0</flags>
            <timecreated>1662402081</timecreated>
            <timemodified>0</timemodified>
            <answer_text>Next</answer_text>
            <response>$@NULL@$</response>
            <answerformat>0</answerformat>
            <responseformat>0</responseformat>
            <attempts>
            </attempts>
          </answer>
        </answers>
        <branches>
        </branches>
      </page>
      <page id="1307">
        <prevpageid>1306</prevpageid>
        <nextpageid>1308</nextpageid>
        <qtype>20</qtype>
        <qoption>0</qoption>
        <layout>1</layout>
        <display>1</display>
        <timecreated>1662406077</timecreated>
        <timemodified>1663666042</timemodified>
        <title>5.8.3: Using Function Language and Notation</title>
        <contents>&lt;div class="os-raise-content" data-content-id="79cda3ad-e022-4f67-aa74-264d2a022f48"&gt;&lt;/div&gt;</contents>
        <contentsformat>1</contentsformat>
        <answers>
          <answer id="2938">
            <jumpto>-40</jumpto>
            <grade>0</grade>
            <score>0</score>
            <flags>0</flags>
            <timecreated>1662406077</timecreated>
            <timemodified>0</timemodified>
            <answer_text>Previous</answer_text>
            <response>$@NULL@$</response>
            <answerformat>0</answerformat>
            <responseformat>0</responseformat>
            <attempts>
            </attempts>
          </answer>
          <answer id="2939">
            <jumpto>-1</jumpto>
            <grade>0</grade>
            <score>0</score>
            <flags>0</flags>
            <timecreated>1662406077</timecreated>
            <timemodified>0</timemodified>
            <answer_text>Next</answer_text>
            <response>$@NULL@$</response>
            <answerformat>0</answerformat>
            <responseformat>0</responseformat>
            <attempts>
            </attempts>
          </answer>
        </answers>
        <branches>
        </branches>
      </page>
      <page id="1308">
        <prevpageid>1307</prevpageid>
        <nextpageid>1309</nextpageid>
        <qtype>20</qtype>
        <qoption>0</qoption>
        <layout>1</layout>
        <display>1</display>
        <timecreated>1662428481</timecreated>
        <timemodified>1663521556</timemodified>
        <title>5.8.4: Function Notation</title>
        <contents>&lt;div class="os-raise-content" data-content-id="338acf83-90ff-4c09-8413-496db6de977f"&gt;&lt;/div&gt;</contents>
        <contentsformat>1</contentsformat>
        <answers>
          <answer id="2940">
            <jumpto>-40</jumpto>
            <grade>0</grade>
            <score>0</score>
            <flags>0</flags>
            <timecreated>1662428481</timecreated>
            <timemodified>0</timemodified>
            <answer_text>Previous</answer_text>
            <response>$@NULL@$</response>
            <answerformat>0</answerformat>
            <responseformat>0</responseformat>
            <attempts>
            </attempts>
          </answer>
          <answer id="2941">
            <jumpto>-1</jumpto>
            <grade>0</grade>
            <score>0</score>
            <flags>0</flags>
            <timecreated>1662428481</timecreated>
            <timemodified>0</timemodified>
            <answer_text>Next</answer_text>
            <response>$@NULL@$</response>
            <answerformat>0</answerformat>
            <responseformat>0</responseformat>
            <attempts>
            </attempts>
          </answer>
        </answers>
        <branches>
        </branches>
      </page>
      <page id="1309">
        <prevpageid>1308</prevpageid>
        <nextpageid>1310</nextpageid>
        <qtype>20</qtype>
        <qoption>0</qoption>
        <layout>1</layout>
        <display>1</display>
        <timecreated>1662428819</timecreated>
        <timemodified>1663701981</timemodified>
        <title>5.8.5: Practice</title>
        <contents>&lt;div class="os-raise-content" data-content-id="5873e1a1-ee03-467d-9ff9-1f93ba3ca1f0"&gt;&lt;/div&gt;</contents>
        <contentsformat>1</contentsformat>
        <answers>
          <answer id="2942">
            <jumpto>-40</jumpto>
            <grade>0</grade>
            <score>0</score>
            <flags>0</flags>
            <timecreated>1662428819</timecreated>
            <timemodified>0</timemodified>
            <answer_text>Previous</answer_text>
            <response>$@NULL@$</response>
            <answerformat>0</answerformat>
            <responseformat>0</responseformat>
            <attempts>
            </attempts>
          </answer>
          <answer id="2943">
            <jumpto>-1</jumpto>
            <grade>0</grade>
            <score>0</score>
            <flags>0</flags>
            <timecreated>1662428819</timecreated>
            <timemodified>0</timemodified>
            <answer_text>Next</answer_text>
            <response>$@NULL@$</response>
            <answerformat>0</answerformat>
            <responseformat>0</responseformat>
            <attempts>
            </attempts>
          </answer>
        </answers>
        <branches>
        </branches>
      </page>
      <page id="1310">
        <prevpageid>1309</prevpageid>
        <nextpageid>0</nextpageid>
        <qtype>20</qtype>
        <qoption>0</qoption>
        <layout>1</layout>
        <display>1</display>
        <timecreated>1662430802</timecreated>
        <timemodified>1663517340</timemodified>
        <title>5.8.6: Lesson Synthesis</title>
        <contents>&lt;div class="os-raise-content" data-content-id="9c521ea9-ba74-425b-8e4c-e9ab12399eb2"&gt;&lt;/div&gt;</contents>
        <contentsformat>1</contentsformat>
        <answers>
          <answer id="2944">
            <jumpto>-40</jumpto>
            <grade>0</grade>
            <score>0</score>
            <flags>0</flags>
            <timecreated>1662430802</timecreated>
            <timemodified>0</timemodified>
            <answer_text>Previous</answer_text>
            <response>$@NULL@$</response>
            <answerformat>0</answerformat>
            <responseformat>0</responseformat>
            <attempts>
            </attempts>
          </answer>
          <answer id="2945">
            <jumpto>-9</jumpto>
            <grade>0</grade>
            <score>0</score>
            <flags>0</flags>
            <timecreated>1662430802</timecreated>
            <timemodified>0</timemodified>
            <answer_text>End of Lesson</answer_text>
            <response>$@NULL@$</response>
            <answerformat>0</answerformat>
            <responseformat>0</responseformat>
            <attempts>
            </attempts>
          </answer>
        </answers>
        <branches>
        </branches>
      </page>
    </pages>
    <grades>
    </grades>
    <timers>
    </timers>
    <overrides>
    </overrides>
  </lesson>
</activity>