<?xml version='1.0' encoding='UTF-8'?>
<activity id="186" moduleid="247" modulename="lesson" contextid="258">
  <lesson id="186">
    <course>2</course>
    <name>Lesson 7.10 Teacher Guide: Graphs of Functions in Standard and Factored Forms</name>
    <intro/>
    <introformat>1</introformat>
    <practice>1</practice>
    <modattempts>0</modattempts>
    <usepassword>0</usepassword>
    <password/>
    <dependency>0</dependency>
    <conditions>O:8:"stdClass":3:{s:9:"timespent";i:0;s:9:"completed";i:0;s:15:"gradebetterthan";i:0;}</conditions>
    <grade>0</grade>
    <custom>1</custom>
    <ongoing>0</ongoing>
    <usemaxgrade>0</usemaxgrade>
    <maxanswers>5</maxanswers>
    <maxattempts>0</maxattempts>
    <review>0</review>
    <nextpagedefault>0</nextpagedefault>
    <feedback>0</feedback>
    <minquestions>0</minquestions>
    <maxpages>1</maxpages>
    <timelimit>0</timelimit>
    <retake>1</retake>
    <activitylink>248</activitylink>
    <mediafile/>
    <mediaheight>480</mediaheight>
    <mediawidth>640</mediawidth>
    <mediaclose>0</mediaclose>
    <slideshow>0</slideshow>
    <width>640</width>
    <height>480</height>
    <bgcolor>#FFFFFF</bgcolor>
    <displayleft>1</displayleft>
    <displayleftif>0</displayleftif>
    <progressbar>0</progressbar>
    <available>0</available>
    <deadline>0</deadline>
    <timemodified>1665638445</timemodified>
    <completionendreached>0</completionendreached>
    <completiontimespent>0</completiontimespent>
    <allowofflineattempts>0</allowofflineattempts>
    <pages>
      <page id="1710">
        <prevpageid>0</prevpageid>
        <nextpageid>1711</nextpageid>
        <qtype>20</qtype>
        <qoption>0</qoption>
        <layout>1</layout>
        <display>1</display>
        <timecreated>1665008411</timecreated>
        <timemodified>1665674653</timemodified>
        <title>7.10.0: Lesson Overview</title>
        <contents>&lt;div class="os-raise-content" data-content-id="43478792-9551-4a9d-ae47-ae127cf1dffd"&gt;&lt;/div&gt;</contents>
        <contentsformat>1</contentsformat>
        <answers>
          <answer id="3842">
            <jumpto>-1</jumpto>
            <grade>0</grade>
            <score>0</score>
            <flags>0</flags>
            <timecreated>1665008411</timecreated>
            <timemodified>0</timemodified>
            <answer_text>Next</answer_text>
            <response>$@NULL@$</response>
            <answerformat>0</answerformat>
            <responseformat>0</responseformat>
            <attempts>
            </attempts>
          </answer>
        </answers>
        <branches>
        </branches>
      </page>
      <page id="1711">
        <prevpageid>1710</prevpageid>
        <nextpageid>1712</nextpageid>
        <qtype>20</qtype>
        <qoption>0</qoption>
        <layout>1</layout>
        <display>1</display>
        <timecreated>1665008431</timecreated>
        <timemodified>1665657371</timemodified>
        <title>7.10.1: Graphs of Linear Equations</title>
        <contents>&lt;div class="os-raise-content" data-content-id="6424036a-3fd8-4bac-9b75-e9f780b99f37"&gt;&lt;/div&gt;</contents>
        <contentsformat>1</contentsformat>
        <answers>
          <answer id="3843">
            <jumpto>-40</jumpto>
            <grade>0</grade>
            <score>0</score>
            <flags>0</flags>
            <timecreated>1665008431</timecreated>
            <timemodified>0</timemodified>
            <answer_text>Previous</answer_text>
            <response>$@NULL@$</response>
            <answerformat>0</answerformat>
            <responseformat>0</responseformat>
            <attempts>
            </attempts>
          </answer>
          <answer id="3844">
            <jumpto>-1</jumpto>
            <grade>0</grade>
            <score>0</score>
            <flags>0</flags>
            <timecreated>1665008431</timecreated>
            <timemodified>0</timemodified>
            <answer_text>Next</answer_text>
            <response>$@NULL@$</response>
            <answerformat>0</answerformat>
            <responseformat>0</responseformat>
            <attempts>
            </attempts>
          </answer>
        </answers>
        <branches>
        </branches>
      </page>
      <page id="1712">
        <prevpageid>1711</prevpageid>
        <nextpageid>1713</nextpageid>
        <qtype>20</qtype>
        <qoption>0</qoption>
        <layout>1</layout>
        <display>1</display>
        <timecreated>1665008860</timecreated>
        <timemodified>1665731098</timemodified>
        <title>7.10.2: Quadratic Forms and Their Graphs</title>
        <contents>&lt;div class="os-raise-content" data-content-id="c005ada3-065f-4c20-8578-390a947bcc6e"&gt;&lt;/div&gt;</contents>
        <contentsformat>1</contentsformat>
        <answers>
          <answer id="3845">
            <jumpto>-40</jumpto>
            <grade>0</grade>
            <score>0</score>
            <flags>0</flags>
            <timecreated>1665008860</timecreated>
            <timemodified>0</timemodified>
            <answer_text>Previous</answer_text>
            <response>$@NULL@$</response>
            <answerformat>0</answerformat>
            <responseformat>0</responseformat>
            <attempts>
            </attempts>
          </answer>
          <answer id="3846">
            <jumpto>-1</jumpto>
            <grade>0</grade>
            <score>0</score>
            <flags>0</flags>
            <timecreated>1665008860</timecreated>
            <timemodified>0</timemodified>
            <answer_text>Next</answer_text>
            <response>$@NULL@$</response>
            <answerformat>0</answerformat>
            <responseformat>0</responseformat>
            <attempts>
            </attempts>
          </answer>
        </answers>
        <branches>
        </branches>
      </page>
      <page id="1713">
        <prevpageid>1712</prevpageid>
        <nextpageid>1714</nextpageid>
        <qtype>20</qtype>
        <qoption>0</qoption>
        <layout>1</layout>
        <display>1</display>
        <timecreated>1665010465</timecreated>
        <timemodified>1665731223</timemodified>
        <title>7.10.3: The X- and Y-Intercepts of Quadratic Expressions</title>
        <contents>&lt;div class="os-raise-content" data-content-id="70d7838f-a7e8-4b5a-af50-9fcccd243c22"&gt;&lt;/div&gt;</contents>
        <contentsformat>1</contentsformat>
        <answers>
          <answer id="3847">
            <jumpto>-40</jumpto>
            <grade>0</grade>
            <score>0</score>
            <flags>0</flags>
            <timecreated>1665010465</timecreated>
            <timemodified>0</timemodified>
            <answer_text>Previous</answer_text>
            <response>$@NULL@$</response>
            <answerformat>0</answerformat>
            <responseformat>0</responseformat>
            <attempts>
            </attempts>
          </answer>
          <answer id="3848">
            <jumpto>-1</jumpto>
            <grade>0</grade>
            <score>0</score>
            <flags>0</flags>
            <timecreated>1665010465</timecreated>
            <timemodified>0</timemodified>
            <answer_text>Next</answer_text>
            <response>$@NULL@$</response>
            <answerformat>0</answerformat>
            <responseformat>0</responseformat>
            <attempts>
            </attempts>
          </answer>
        </answers>
        <branches>
        </branches>
      </page>
      <page id="1714">
        <prevpageid>1713</prevpageid>
        <nextpageid>1715</nextpageid>
        <qtype>20</qtype>
        <qoption>0</qoption>
        <layout>1</layout>
        <display>1</display>
        <timecreated>1665013223</timecreated>
        <timemodified>1665685696</timemodified>
        <title>7.10.4: Using the Standard Form of an Equation to Find the X- and Y-Intercepts </title>
        <contents>&lt;div class="os-raise-content" data-content-id="8d864fc2-46b4-4606-9842-870a461d7909"&gt;&lt;/div&gt;</contents>
        <contentsformat>1</contentsformat>
        <answers>
          <answer id="3849">
            <jumpto>-40</jumpto>
            <grade>0</grade>
            <score>0</score>
            <flags>0</flags>
            <timecreated>1665013223</timecreated>
            <timemodified>0</timemodified>
            <answer_text>Previous</answer_text>
            <response>$@NULL@$</response>
            <answerformat>0</answerformat>
            <responseformat>0</responseformat>
            <attempts>
            </attempts>
          </answer>
          <answer id="3850">
            <jumpto>-1</jumpto>
            <grade>0</grade>
            <score>0</score>
            <flags>0</flags>
            <timecreated>1665013223</timecreated>
            <timemodified>0</timemodified>
            <answer_text>Next</answer_text>
            <response>$@NULL@$</response>
            <answerformat>0</answerformat>
            <responseformat>0</responseformat>
            <attempts>
            </attempts>
          </answer>
        </answers>
        <branches>
        </branches>
      </page>
      <page id="1715">
        <prevpageid>1714</prevpageid>
        <nextpageid>1716</nextpageid>
        <qtype>20</qtype>
        <qoption>0</qoption>
        <layout>1</layout>
        <display>1</display>
        <timecreated>1665013520</timecreated>
        <timemodified>1665731737</timemodified>
        <title>7.10.5: Practice </title>
        <contents>&lt;div class="os-raise-content" data-content-id="15825330-53fd-43cb-b344-9630bdc8d55b"&gt;&lt;/div&gt;</contents>
        <contentsformat>1</contentsformat>
        <answers>
          <answer id="3851">
            <jumpto>-40</jumpto>
            <grade>0</grade>
            <score>0</score>
            <flags>0</flags>
            <timecreated>1665013520</timecreated>
            <timemodified>0</timemodified>
            <answer_text>Previous</answer_text>
            <response>$@NULL@$</response>
            <answerformat>0</answerformat>
            <responseformat>0</responseformat>
            <attempts>
            </attempts>
          </answer>
          <answer id="3852">
            <jumpto>-1</jumpto>
            <grade>0</grade>
            <score>0</score>
            <flags>0</flags>
            <timecreated>1665013520</timecreated>
            <timemodified>0</timemodified>
            <answer_text>Next</answer_text>
            <response>$@NULL@$</response>
            <answerformat>0</answerformat>
            <responseformat>0</responseformat>
            <attempts>
            </attempts>
          </answer>
        </answers>
        <branches>
        </branches>
      </page>
      <page id="1716">
        <prevpageid>1715</prevpageid>
        <nextpageid>0</nextpageid>
        <qtype>20</qtype>
        <qoption>0</qoption>
        <layout>1</layout>
        <display>1</display>
        <timecreated>1665014767</timecreated>
        <timemodified>1665014828</timemodified>
        <title>7.10.6: Lesson Synthesis </title>
        <contents>&lt;div class="os-raise-content" data-content-id="f61b0ffd-da36-4232-bbe2-619b6716baf3"&gt;&lt;/div&gt;</contents>
        <contentsformat>1</contentsformat>
        <answers>
          <answer id="3853">
            <jumpto>-40</jumpto>
            <grade>0</grade>
            <score>0</score>
            <flags>0</flags>
            <timecreated>1665014767</timecreated>
            <timemodified>0</timemodified>
            <answer_text>Previous</answer_text>
            <response>$@NULL@$</response>
            <answerformat>0</answerformat>
            <responseformat>0</responseformat>
            <attempts>
            </attempts>
          </answer>
          <answer id="3854">
            <jumpto>-9</jumpto>
            <grade>0</grade>
            <score>0</score>
            <flags>0</flags>
            <timecreated>1665014767</timecreated>
            <timemodified>0</timemodified>
            <answer_text>End of Lesson</answer_text>
            <response>$@NULL@$</response>
            <answerformat>0</answerformat>
            <responseformat>0</responseformat>
            <attempts>
            </attempts>
          </answer>
        </answers>
        <branches>
        </branches>
      </page>
    </pages>
    <grades>
    </grades>
    <timers>
    </timers>
    <overrides>
    </overrides>
  </lesson>
</activity>
